wetransfer/__init__.py
wetransfer/main.py
wetransfer_upload-0.0.5.dist-info/DESCRIPTION.rst
wetransfer_upload-0.0.5.dist-info/METADATA
wetransfer_upload-0.0.5.dist-info/RECORD
wetransfer_upload-0.0.5.dist-info/WHEEL
wetransfer_upload-0.0.5.dist-info/metadata.json
wetransfer_upload-0.0.5.dist-info/top_level.txt
