Metadata-Version: 2.0
Name: wetransfer-upload
Version: 0.0.5
Summary: Upload files to WeTransfer
Home-page: https://github.com/creemerica/wetransfer-upload
Author: Spencer Cree
Author-email: UNKNOWN
License: MIT
Keywords: wetransfer,upload
Platform: UNKNOWN
Classifier: Development Status :: 3 - Alpha
Classifier: Intended Audience :: Developers
Classifier: Topic :: Software Development :: Build Tools
Classifier: License :: OSI Approved :: MIT License
Classifier: Programming Language :: Python :: 2.7
Classifier: Programming Language :: Python :: 3
Classifier: Programming Language :: Python :: 3.2
Classifier: Programming Language :: Python :: 3.3
Classifier: Programming Language :: Python :: 3.4
Requires-Dist: requests (==2.7.0)
Requires-Dist: requests-toolbelt (==0.4.0)
